lilytk/__init__.py
lilytk/typing.py
lilytk/capabilities/__init__.py
lilytk/capabilities/highlightable.py
lilytk/capabilities/scrollable.py
lilytk/events/__init__.py
lilytk/events/notify_listen.py
lilytk/utils/__init__.py
lilytk/utils/debug.py
lilytk/utils/singleton.py
lilytk/widgets/__init__.py
lilytk/widgets/scrollable_frame.py
lilytk-0.2.0.dist-info/METADATA
lilytk-0.2.0.dist-info/WHEEL
lilytk-0.2.0.dist-info/licenses/LICENSE
lilytk-0.2.0.dist-info/RECORD
